synthtexteval/__init__.py
synthtexteval/eval/descriptive/README.md
synthtexteval/eval/descriptive/__init__.py
synthtexteval/eval/descriptive/arguments.py
synthtexteval/eval/descriptive/compare.py
synthtexteval/eval/descriptive/descriptor.py
synthtexteval/eval/descriptive/distributional_difference.py
synthtexteval/eval/descriptive/test.py
synthtexteval/eval/downstream/README.md
synthtexteval/eval/downstream/__init__.py
synthtexteval/eval/downstream/classify/__init__.py
synthtexteval/eval/downstream/classify/generate_silver_annotations.py
synthtexteval/eval/downstream/classify/run-train.sh
synthtexteval/eval/downstream/classify/test_silver.py
synthtexteval/eval/downstream/classify/train.sh
synthtexteval/eval/downstream/classify/train_classifier.py
synthtexteval/eval/downstream/classify/utils.py
synthtexteval/eval/downstream/classify/visualize.py
synthtexteval/eval/downstream/coref/__init__.py
synthtexteval/eval/downstream/coref/arguments.py
synthtexteval/eval/downstream/coref/cli.py
synthtexteval/eval/downstream/coref/conll.py
synthtexteval/eval/downstream/coref/consts.py
synthtexteval/eval/downstream/coref/coref_bucket_batch_sampler.py
synthtexteval/eval/downstream/coref/coref_requirements.txt
synthtexteval/eval/downstream/coref/data.py
synthtexteval/eval/downstream/coref/eval.py
synthtexteval/eval/downstream/coref/infer.py
synthtexteval/eval/downstream/coref/metrics.py
synthtexteval/eval/downstream/coref/minimize_synth.py
synthtexteval/eval/downstream/coref/modeling.py
synthtexteval/eval/downstream/coref/run-server.sh
synthtexteval/eval/downstream/coref/run.sh
synthtexteval/eval/downstream/coref/run_coref_comparison.py
synthtexteval/eval/downstream/coref/test.ipynb
synthtexteval/eval/downstream/coref/text-mimic.txt
synthtexteval/eval/downstream/coref/text.txt
synthtexteval/eval/downstream/coref/training.py
synthtexteval/eval/downstream/coref/utils.py
synthtexteval/eval/fairness/README.md
synthtexteval/eval/fairness/__init__.py
synthtexteval/eval/fairness/fair.sh
synthtexteval-1.1.1.dist-info/licenses/LICENSE
synthtexteval-1.1.1.dist-info/METADATA
synthtexteval-1.1.1.dist-info/WHEEL
synthtexteval-1.1.1.dist-info/top_level.txt
synthtexteval-1.1.1.dist-info/RECORD
